docs/__init__.py
docs/conf.py
mpesa/__init__.py
mpesa/api/__init__.py
mpesa/api/auth.py
mpesa/api/b2b.py
mpesa/api/b2c.py
mpesa/api/balance.py
mpesa/api/c2b.py
mpesa/api/mpesa_express.py
mpesa/api/reversal.py
mpesa/api/transaction_status.py
mpesa/tests/__init__.py
mpesa/tests/test_auth.py
mpesa/tests/test_b2b.py
mpesa/tests/test_b2c.py
mpesa/tests/test_balance.py
mpesa/tests/test_c2b.py
mpesa/tests/test_mpesa_express.py
mpesa/tests/test_reversal.py
mpesa/tests/test_transaction_status.py
daraja_mpesa-1.2.dist-info/LICENSE
daraja_mpesa-1.2.dist-info/METADATA
daraja_mpesa-1.2.dist-info/WHEEL
daraja_mpesa-1.2.dist-info/top_level.txt
daraja_mpesa-1.2.dist-info/RECORD
