Metadata-Version: 2.1
Name: daraja-mpesa
Version: 1.2
Summary: A Python wrapper for Mpesa Daraja APIs abstracting raw https request
Home-page: https://github.com/TralahM/pympesa
Author: Tralah M Brian
Author-email: briantralah@gmail.com
License: UNKNOWN
Platform: UNKNOWN
Classifier: Programming Language :: Python
Classifier: License :: OSI Approved :: MIT License
Classifier: Operating System :: OS Independent
Requires-Dist: certifi
Requires-Dist: chardet
Requires-Dist: future
Requires-Dist: idna
Requires-Dist: requests
Requires-Dist: six
Requires-Dist: urllib3
